llmdebug/__init__.py
llmdebug/async_context.py
llmdebug/capture.py
llmdebug/compact_keys.py
llmdebug/config.py
llmdebug/error_categories.py
llmdebug/git_context.py
llmdebug/log_capture.py
llmdebug/output.py
llmdebug/py.typed
llmdebug/pytest_plugin.py
llmdebug/serialize.py
llmdebug/toon_encoder.py
llmdebug-2.0.0.dist-info/METADATA
llmdebug-2.0.0.dist-info/WHEEL
llmdebug-2.0.0.dist-info/entry_points.txt
llmdebug-2.0.0.dist-info/licenses/LICENSE
llmdebug-2.0.0.dist-info/RECORD
