Metadata-Version: 2.4
Name: llmdebug
Version: 2.0.0
Summary: Structured debug snapshots for LLM-assisted debugging
Project-URL: Homepage, https://github.com/NicolasSchuler/llmdebug
Project-URL: Repository, https://github.com/NicolasSchuler/llmdebug
Author-email: Nicolas Schuler <schuler.nicolas@proton.me>
License: MIT
License-File: LICENSE
Keywords: crash-reporting,debugging,llm,pytest
Classifier: Development Status :: 4 - Beta
Classifier: Framework :: Pytest
Classifier: Intended Audience :: Developers
Classifier: License :: OSI Approved :: MIT License
Classifier: Programming Language :: Python :: 3
Classifier: Programming Language :: Python :: 3.10
Classifier: Programming Language :: Python :: 3.11
Classifier: Programming Language :: Python :: 3.12
Classifier: Programming Language :: Python :: 3.13
Classifier: Topic :: Software Development :: Debuggers
Requires-Python: >=3.10
Requires-Dist: filelock>=3.0
Provides-Extra: dev
Requires-Dist: numpy>=1.20; extra == 'dev'
Requires-Dist: pyright>=1.1; extra == 'dev'
Requires-Dist: pytest-asyncio>=0.21; extra == 'dev'
Requires-Dist: pytest-benchmark>=4.0; extra == 'dev'
Requires-Dist: pytest>=7.0; extra == 'dev'
Requires-Dist: python-semantic-release>=9.0; extra == 'dev'
Requires-Dist: ruff>=0.1; extra == 'dev'
Requires-Dist: toons>=0.1; extra == 'dev'
Provides-Extra: toon
Requires-Dist: toons>=0.1; extra == 'toon'
